README.md
setup.py
evohome/__init__.py
evohome/command.py
evohome/const.py
evohome/controller.py
evohome/entity.py
evohome/logger.py
evohome/message.py
evohome.egg-info/PKG-INFO
evohome.egg-info/SOURCES.txt
evohome.egg-info/dependency_links.txt
evohome.egg-info/top_level.txt